{"citations": [{"Paper_link": "http://www.tandfonline.com/doi/abs/10.1080/05704927908060396", "Title": "Systematic organic UV photoelectron spectroscopy", "authors": ["CNR Rao", "PK Basu", "MS Hegde "], "Citations_Link": "https://scholar.google.com/scholar?cites=7012102871167452418&as_sdt=2005&sciodt=0,5&hl=en&num=20"}, {"Paper_link": "http://scitation.aip.org/content/aip/journal/jcp/72/4/10.1063/1.439427", "Title": "Variable angle electron\u2010impact excitation of nitromethane", "authors": ["WM Flicker", "OA Mosher "], "Citations_Link": "https://scholar.google.com/scholar?cites=3669642617913412193&as_sdt=2005&sciodt=0,5&hl=en&num=20"}, {"Paper_link": "http://www.sciencedirect.com/science/article/pii/036820489185025O", "Title": "He (I) and He (II) photoelectron spectra of simple nitroalkanes", "authors": ["CY Mok", "WS Chin", "HH Huang "], "Citations_Link": "https://scholar.google.com/scholar?cites=3852391202185608807&as_sdt=2005&sciodt=0,5&hl=en&num=20"}, {"Paper_link": "http://pubs.rsc.org/en/content/articlehtml/1991/ft/ft9918701685", "Title": "He I and He II photoelectron spectra of isomeric nitropropenes", "authors": ["WS Chin", "CY Mok", "HH Huang "], "Citations_Link": "https://scholar.google.com/scholar?cites=2689085408012210385&as_sdt=2005&sciodt=0,5&hl=en&num=20"}, {"Paper_link": "http://onlinelibrary.wiley.com/doi/10.1002/9780470682531.pat0074/full", "Title": "Photoelectron spectra of amines, nitroso and nitro compounds", "authors": ["P Rademacher "], "Citations_Link": "https://scholar.google.com/scholar?cites=10290361533166962993&as_sdt=2005&sciodt=0,5&hl=en&num=20"}, {"Paper_link": null, "Title": "[CITATION][C] THERMAL DECOMPOSITION OF 1-NITROPROPANE AND N-PROPYL NITRITE-ANALYSIS OF PRODUCT BY PHOTOELECTRON SPECTROSCOPY", "authors": ["WS Chin", "CY Mok", "HH Huang "], "Citations_Link": "https://scholar.google.com/scholar?q=related:8eFKRc2iwhAJ:scholar.google.com/&hl=en&num=20&as_sdt=0,5&sciodt=0,5"}], "paper_link": "https://scholar.google.com/citations?view_op=view_citation&hl=en&user=Zs9227oAAAAJ&cstart=1459&pagesize=100&citation_for_view=Zs9227oAAAAJ:4p5LGG1h9z0C", "authors": ["CNR Rao"], "title": "PHOTOELECTRON-SPECTRA OF C-NITRO AND N-NITRO COMPOUNDS", "publication": "INDIAN JOURNAL OF CHEMISTRY SECTION A-INORGANIC BIO-INORGANIC PHYSICAL ..., 1976"}