{"publication": "Chemistry of materials 9 (10), 2078-2081, 1997", "citations": [{"Citations_Link": "https://scholar.google.com/scholar?cites=10028272982586589519&as_sdt=2005&sciodt=0,5&hl=en&num=20", "Paper_link": "http://pubs.acs.org/doi/abs/10.1021/cr030063a", "authors": ["C Burda", "X Chen", "R Narayanan", "MA El"], "Title": "Chemistry and properties of nanocrystals of different shapes"}, {"Citations_Link": "https://scholar.google.com/scholar?cites=7982850540634704038&as_sdt=2005&sciodt=0,5&hl=en&num=20", "Paper_link": "http://www.sciencedirect.com/science/article/pii/S0009261499010295", "authors": ["P Nikolaev", "MJ Bronikowski", "RK Bradley "], "Title": "Gas-phase catalytic growth of single-walled carbon nanotubes from carbon monoxide"}, {"Citations_Link": "https://scholar.google.com/scholar?cites=8912278883651540526&as_sdt=2005&sciodt=0,5&hl=en&num=20", "Paper_link": "http://www.annualreviews.org/doi/abs/10.1146/annurev.matsci.33.012802.100255", "authors": ["M Terrones "], "Title": "Science and technology of the twenty-first century: synthesis, properties, and applications of carbon nanotubes"}, {"Citations_Link": "https://scholar.google.com/scholar?cites=15585068576046825856&as_sdt=2005&sciodt=0,5&hl=en&num=20", "Paper_link": "http://www.chimdocet-solido.it/PDF_Link/ORGANOMET.pdf", "authors": ["AL Balch", "MM Olmstead "], "Title": "Reactions of Transition Metal Complexes with Fullerenes (C~ 6~ 0, C~ 7~ 0, etc.) and Related Materials"}, {"Citations_Link": "https://scholar.google.com/scholar?cites=148405259168332749&as_sdt=2005&sciodt=0,5&hl=en&num=20", "Paper_link": "http://www.sciencedirect.com/science/article/pii/S0009261498002206", "authors": ["R Sen", "BC Satishkumar", "A Govindaraj "], "Title": "B\u2013C\u2013N, C\u2013N and B\u2013N nanotubes produced by the pyrolysis of precursor molecules over Co catalysts"}, {"Citations_Link": "https://scholar.google.com/scholar?cites=7642867803524531864&as_sdt=2005&sciodt=0,5&hl=en&num=20", "Paper_link": "http://pubs.rsc.org/en/content/articlehtml/2013/cs/c2cs35335k", "authors": ["D Jariwala", "VK Sangwan", "LJ Lauhon "], "Title": "Carbon nanomaterials for electronics, optoelectronics, photovoltaics, and sensing"}, {"Citations_Link": "https://scholar.google.com/scholar?cites=12548311422646572120&as_sdt=2005&sciodt=0,5&hl=en&num=20", "Paper_link": "http://pubs.acs.org/doi/abs/10.1021/cm9802191", "authors": ["A Clearfield "], "Title": "Organically pillared micro-and mesoporous materials"}, {"Citations_Link": "https://scholar.google.com/scholar?cites=91428848324884032&as_sdt=2005&sciodt=0,5&hl=en&num=20", "Paper_link": "http://pubs.rsc.org/en/content/articlehtml/2004/jm/b308124a", "authors": ["XR Ye", "Y Lin", "C Wang", "MH Engelhard "], "Title": "Supercritical fluid synthesis and characterization of catalytic metal nanoparticles on carbon nanotubes"}, {"Citations_Link": "https://scholar.google.com/scholar?cites=17087140959996034069&as_sdt=2005&sciodt=0,5&hl=en&num=20", "Paper_link": "http://link.springer.com/article/10.1007/s003390100929", "authors": ["A Huczko "], "Title": "Synthesis of aligned carbon nanotubes"}, {"Citations_Link": "https://scholar.google.com/scholar?cites=4126825437473094427&as_sdt=2005&sciodt=0,5&hl=en&num=20", "Paper_link": "https://books.google.com/books?hl=en&lr=&id=lhteFnh8BtkC&oi=fnd&pg=PA1&ots=wy8ns06EIL&sig=170PK7f--AjGo8qTPOODr7WSPjw", "authors": ["CNR Rao", "A Govindaraj "], "Title": "Nanotubes and nanowires"}, {"Citations_Link": "https://scholar.google.com/scholar?cites=14471470847236275663&as_sdt=2005&sciodt=0,5&hl=en&num=20", "Paper_link": "http://www-g.eng.cam.ac.uk/cnt/oldsite/papers/ken_enn.pdf", "authors": ["KBK Teo", "C Singh", "M Chhowalla "], "Title": "Catalytic synthesis of carbon nanotubes and nanofibers"}, {"Citations_Link": "https://scholar.google.com/scholar?cites=16092420680381208907&as_sdt=2005&sciodt=0,5&hl=en&num=20", "Paper_link": "http://onlinelibrary.wiley.com/doi/10.1002/adma.200390077/full", "authors": ["XR Ye", "Y Lin", "C Wang", "CM Wai "], "Title": "Supercritical fluid fabrication of metal nanowires and nanorods templated by multiwalled carbon nanotubes"}, {"Citations_Link": "https://scholar.google.com/scholar?cites=8718422519853311570&as_sdt=2005&sciodt=0,5&hl=en&num=20", "Paper_link": "http://pubs.acs.org/doi/abs/10.1021/ar0101584", "authors": ["CNR Rao", "A Govindaraj "], "Title": "Carbon nanotubes from organometallic precursors"}, {"Citations_Link": "https://scholar.google.com/scholar?cites=11160511931130398930&as_sdt=2005&sciodt=0,5&hl=en&num=20", "Paper_link": "http://www.sciencedirect.com/science/article/pii/S0009250906001278", "authors": ["A Moisala", "AG Nasibulin", "DP Brown", "H Jiang "], "Title": "Single-walled carbon nanotube synthesis using ferrocene and iron pentacarbonyl in a laminar flow reactor"}, {"Citations_Link": "https://scholar.google.com/scholar?cites=7547797101380562712&as_sdt=2005&sciodt=0,5&hl=en&num=20", "Paper_link": "http://onlinelibrary.wiley.com/doi/10.1002/cssc.201100177/full", "authors": ["Q Zhang", "JQ Huang", "MQ Zhao", "WZ Qian "], "Title": "Carbon nanotube mass production: principles and processes"}, {"Citations_Link": "https://scholar.google.com/scholar?cites=15728585175353084004&as_sdt=2005&sciodt=0,5&hl=en&num=20", "Paper_link": "http://onlinelibrary.wiley.com/doi/10.1002/elan.200403120/abstract", "authors": ["NS Lawrence", "RP Deo", "J Wang "], "Title": "Comparison of the electrochemical reactivity of electrodes modified with carbon nanotubes from different sources"}, {"Citations_Link": "https://scholar.google.com/scholar?cites=7931308850073464082&as_sdt=2005&sciodt=0,5&hl=en&num=20", "Paper_link": "http://pubs.acs.org/doi/abs/10.1021/cm000062o", "authors": ["S Liu", "J Zhu", "Y Mastai", "I Felner "], "Title": "Preparation and characteristics of carbon nanotubes filled with cobalt"}, {"Citations_Link": "https://scholar.google.com/scholar?cites=8113337377477504164&as_sdt=2005&sciodt=0,5&hl=en&num=20", "Paper_link": "http://www.sciencedirect.com/science/article/pii/S0008622303001271", "authors": ["ZH Wang", "CJ Choi", "BK Kim", "JC Kim", "ZD Zhang "], "Title": "Characterization and magnetic properties of carbon-coated cobalt nanocapsules synthesized by the chemical vapor-condensation process"}, {"Citations_Link": "https://scholar.google.com/scholar?cites=2276213127245453305&as_sdt=2005&sciodt=0,5&hl=en&num=20", "Paper_link": "http://pubs.rsc.org/en/content/articlehtml/2001/jm/b009775f", "authors": ["OA Nerushev", "M Sveningsson", "LKL Falk "], "Title": "Carbon nanotube films obtained by thermal chemical vapour deposition"}, {"Citations_Link": "https://scholar.google.com/scholar?cites=7016479804816808500&as_sdt=2005&sciodt=0,5&hl=en&num=20", "Paper_link": "http://onlinelibrary.wiley.com/doi/10.1002/adma.200305296/full", "authors": ["J Jang", "H Yoon "], "Title": "Fabrication of Magnetic Carbon Nanotubes Using a Metal\u2010Impregnated Polymer Precursor"}, {"Citations_Link": "https://scholar.google.com/scholar?cites=5810425269635015445&as_sdt=2005&sciodt=0,5&hl=en&num=20", "Paper_link": "http://www.sciencedirect.com/science/article/pii/S0009261403005311", "authors": ["C Singh", "MSP Shaffer", "KKK Koziol", "IA Kinloch "], "Title": "Towards the production of large-scale aligned carbon nanotubes"}, {"Citations_Link": "https://scholar.google.com/scholar?cites=15258489389167642351&as_sdt=2005&sciodt=0,5&hl=en&num=20", "Paper_link": "http://pubs.rsc.org/en/content/articlehtml/1999/jm/a804467h", "authors": ["CNR Rao "], "Title": "Novel materials, materials design and synthetic strategies: recent advances and new directions"}, {"Citations_Link": "https://scholar.google.com/scholar?cites=10626321815932157303&as_sdt=2005&sciodt=0,5&hl=en&num=20", "Paper_link": "http://www.ingentaconnect.com/content/asp/jnn/2005/00000005/00000010/art00004", "authors": ["K Awasthi", "A Srivastava "], "Title": "Synthesis of carbon nanotubes"}, {"Citations_Link": "https://scholar.google.com/scholar?cites=16659566256795510139&as_sdt=2005&sciodt=0,5&hl=en&num=20", "Paper_link": "http://onlinelibrary.wiley.com/doi/10.1002/(SICI)1099-1581(199907)10:7%3C357::AID-PAT886%3E3.0.CO;2-9/full", "authors": ["L Dai "], "Title": "Advanced syntheses and microfabrications of conjugated polymers, C60\u2010containing polymers and carbon nanotubes for optoelectronic applications"}, {"Citations_Link": "https://scholar.google.com/scholar?cites=11609219498582430434&as_sdt=2005&sciodt=0,5&hl=en&num=20", "Paper_link": "http://pubs.acs.org/doi/abs/10.1021/cm021290g", "authors": ["H Hou", "Z Jun", "F Weller", "A Greiner "], "Title": "Large-scale synthesis and characterization of helically coiled carbon nanotubes by use of Fe (CO) 5 as floating catalyst precursor"}, {"Citations_Link": "https://scholar.google.com/scholar?cites=5953115469456038474&as_sdt=2005&sciodt=0,5&hl=en&num=20", "Paper_link": "http://www.sciencedirect.com/science/article/pii/S0009261402006553", "authors": ["CJ Lee", "SC Lyu", "HW Kim", "JH Lee", "KI Cho "], "Title": "Synthesis of bamboo-shaped carbon\u2013nitrogen nanotubes using C 2 H 2\u2013NH 3\u2013Fe (CO) 5 system"}, {"Citations_Link": "https://scholar.google.com/scholar?cites=7091354827835472884&as_sdt=2005&sciodt=0,5&hl=en&num=20", "Paper_link": "http://pubs.rsc.org/en/content/articlehtml/2001/rc/rc010827", "authors": ["EG Rakov "], "Title": "The chemistry and application of carbon nanotubes"}, {"Citations_Link": "https://scholar.google.com/scholar?cites=17568658751540232573&as_sdt=2005&sciodt=0,5&hl=en&num=20", "Paper_link": "http://www.ingentaconnect.com/content/asp/jnn/2007/00000007/f0020004/art00012", "authors": ["W Wei", "A Sethuraman", "C Jin "], "Title": "Biological properties of carbon nanotubes"}, {"Citations_Link": "https://scholar.google.com/scholar?cites=9729449287094357448&as_sdt=2005&sciodt=0,5&hl=en&num=20", "Paper_link": "http://scitation.aip.org/content/aip/journal/apl/84/2/10.1063/1.1639509", "authors": ["RG Lacerda", "AS Teh", "MH Yang", "KBK Teo "], "Title": "Growth of high-quality single-wall carbon nanotubes without amorphous carbon formation"}, {"Citations_Link": "https://scholar.google.com/scholar?cites=5986807684890059289&as_sdt=2005&sciodt=0,5&hl=en&num=20", "Paper_link": "http://link.springer.com/article/10.1007/s100190050075", "authors": ["CNR Rao", "A Govindaraj", "R Sen "], "Title": "Synthesis of multi-walled and single-walled nanotubes, aligned-nanotube bundles and nanorods by employing organometallic precursors"}, {"Citations_Link": "https://scholar.google.com/scholar?cites=3791899806587782104&as_sdt=2005&sciodt=0,5&hl=en&num=20", "Paper_link": "http://www.sciencedirect.com/science/article/pii/S0009261404001320", "authors": ["SRC Vivekchand", "LM Cele", "FL Deepak", "AR Raju "], "Title": "Carbon nanotubes by nebulized spray pyrolysis"}, {"Citations_Link": "https://scholar.google.com/scholar?cites=7632962814029355488&as_sdt=2005&sciodt=0,5&hl=en&num=20", "Paper_link": "http://www.sciencedirect.com/science/article/pii/S0009261400009969", "authors": ["F Rohmund", "LKL Falk", "EEB Campbell "], "Title": "A simple method for the production of large arrays of aligned carbon nanotubes"}, {"Citations_Link": "https://scholar.google.com/scholar?cites=7260673371408066020&as_sdt=2005&sciodt=0,5&hl=en&num=20", "Paper_link": "http://www.sciencedirect.com/science/article/pii/S0009261403009874", "authors": ["JE Herrera", "DE Resasco "], "Title": "In situ TPO/Raman to characterize single-walled carbon nanotubes"}, {"Citations_Link": "https://scholar.google.com/scholar?cites=13793751373273831563&as_sdt=2005&sciodt=0,5&hl=en&num=20", "Paper_link": "http://pubs.rsc.org/en/content/articlehtml/2011/ee/c0ee00256a", "authors": ["VG Pol", "MM Thackeray "], "Title": "Spherical carbon particles and carbon nanotubes prepared by autogenic reactions: Evaluation as anodes in lithium electrochemical cells"}, {"Citations_Link": "https://scholar.google.com/scholar?cites=16777339418625975898&as_sdt=2005&sciodt=0,5&hl=en&num=20", "Paper_link": "http://www.sciencedirect.com/science/article/pii/S0022328X08002155", "authors": ["VO Nyamori", "SD Mhlanga", "NJ Coville "], "Title": "The use of organometallic transition metal complexes in the synthesis of shaped carbon nanomaterials"}, {"Citations_Link": "https://scholar.google.com/scholar?cites=3260858903077096693&as_sdt=2005&sciodt=0,5&hl=en&num=20", "Paper_link": "http://www.ingentaconnect.com/content/asp/jnn/2004/00000004/00000004/art00002", "authors": ["P Nikolaev "], "Title": "Gas-phase production of single-walled carbon nanotubes from carbon monoxide: a review of the HiPco process"}, {"Citations_Link": "https://scholar.google.com/scholar?cites=6734047421541330483&as_sdt=2005&sciodt=0,5&hl=en&num=20", "Paper_link": "http://onlinelibrary.wiley.com/doi/10.1002/smll.200500150/full", "authors": ["L Zhi", "T Gorelik", "R Friedlein", "J Wu", "U Kolb "], "Title": "Solid\u2010State Pyrolyses of Metal Phthalocyanines: A Simple Approach towards Nitrogen\u2010Doped CNTs and Metal/Carbon Nanocables"}, {"Citations_Link": "https://scholar.google.com/scholar?cites=2106680135080494061&as_sdt=2005&sciodt=0,5&hl=en&num=20", "Paper_link": "http://pubs.acs.org/doi/abs/10.1021/cm9904180", "authors": ["W Han", "P Kohler"], "Title": "Formation of (BN) x C y and BN nanotubes filled with boron carbide nanowires"}, {"Citations_Link": "https://scholar.google.com/scholar?cites=10414700007842059336&as_sdt=2005&sciodt=0,5&hl=en&num=20", "Paper_link": "http://pubs.rsc.org/en/content/articlehtml/2000/jm/b004901h", "authors": ["S Liu", "X Tang", "Y Mastai", "I Felner "], "Title": "Preparation and characterization of iron-encapsulatingcarbon nanotubes and nanoparticles"}, {"Citations_Link": "https://scholar.google.com/scholar?cites=7621500434684659339&as_sdt=2005&sciodt=0,5&hl=en&num=20", "Paper_link": "http://www.sciencedirect.com/science/article/pii/S0008622306002983", "authors": ["J Qiu", "Q Li", "Z Wang", "Y Sun", "H Zhang "], "Title": "CVD synthesis of coal-gas-derived carbon nanotubes and nanocapsules containing magnetic iron carbide and oxide"}, {"Citations_Link": "https://scholar.google.com/scholar?cites=14054442034368505990&as_sdt=2005&sciodt=0,5&hl=en&num=20", "Paper_link": "http://journals.cambridge.org/abstract_S0884291400063184", "authors": ["M Zhang", "Y Bando", "K Wada "], "Title": "Synthesis of coaxial nanotubes: Titanium oxide sheathed with silicon oxide"}, {"Citations_Link": "https://scholar.google.com/scholar?cites=6711006252257158789&as_sdt=2005&sciodt=0,5&hl=en&num=20", "Paper_link": "http://onlinelibrary.wiley.com/doi/10.1002/adma.200390078/full", "authors": ["BH Juarez", "M Ibisate", "JM Palacios "], "Title": "High\u2010Energy Photonic Bandgap in Sb2S3 Inverse Opals by Sulfidation Processing"}, {"Citations_Link": "https://scholar.google.com/scholar?cites=18401266473233917739&as_sdt=2005&sciodt=0,5&hl=en&num=20", "Paper_link": "http://www.sciencedirect.com/science/article/pii/S0008622303001854", "authors": ["J Cheng", "X Zhang", "F Liu", "J Tu", "Y Ye", "Y Ji", "C Chen "], "Title": "Synthesis of carbon nanotubes filled with Fe 3 C nanowires by CVD with titanate modified palygorskite as catalyst"}, {"Citations_Link": "https://scholar.google.com/scholar?cites=17413567958217016329&as_sdt=2005&sciodt=0,5&hl=en&num=20", "Paper_link": "http://pubs.rsc.org/en/content/articlehtml/2002/jm/b200470d", "authors": ["HQ Wu", "XW Wei", "MW Shao", "JS Gu "], "Title": "Preparation of Fe\u2013Ni alloy nanoparticles inside carbon nanotubes via wet chemistry"}, {"Citations_Link": "https://scholar.google.com/scholar?cites=14759093856378203424&as_sdt=2005&sciodt=0,5&hl=en&num=20", "Paper_link": "http://www.degruyter.com/view/j/pac.2002.74.issue-9/pac200274091571/pac200274091571.xml", "authors": ["A Govindaraj", "CNR Rao "], "Title": "Organometallic precursor route to carbon nanotubes"}, {"Citations_Link": "https://scholar.google.com/scholar?cites=7327568369694352964&as_sdt=2005&sciodt=0,5&hl=en&num=20", "Paper_link": "https://books.google.com/books?hl=en&lr=&id=cmmQBsZvxp4C&oi=fnd&pg=PR7&ots=rD-u1t6h-D&sig=KZGMRsoRlKLTfb7zDzStYHfLvLY", "authors": ["M Nosonovsky", "PK Rohatgi "], "Title": "Biomimetics in materials science: self-healing, self-lubricating, and self-cleaning materials"}, {"Citations_Link": "https://scholar.google.com/scholar?cites=5455595368771384270&as_sdt=2005&sciodt=0,5&hl=en&num=20", "Paper_link": "http://onlinelibrary.wiley.com/doi/10.1002/adfm.200700296/full", "authors": ["ZG Chen", "J Zou", "F Li", "G Liu", "DM Tang "], "Title": "Growth of Magnetic Yard\u2010Glass Shaped Boron Nitride Nanotubes with Periodic Iron Nanoparticles"}, {"Citations_Link": "https://scholar.google.com/scholar?cites=6646325992631383535&as_sdt=2005&sciodt=0,5&hl=en&num=20", "Title": "[CITATION][C] Carbon nanotubes produced by substrate free metalorganic chemical vapor deposition of iron catalysts and ethylene", "authors": ["R Marangoni", "P Serp", "R Feurer", "Y Kihn", "P Kalck "], "Paper_link": null}, {"Citations_Link": "https://scholar.google.com/scholar?cites=8663947628527055403&as_sdt=2005&sciodt=0,5&hl=en&num=20", "Paper_link": "http://www.sciencedirect.com/science/article/pii/S037967790200005X", "authors": ["ZJ Liu", "R Che", "Z Xu", "LM Peng "], "Title": "Preparation of Fe-filled carbon nanotubes by catalytic decomposition of cyclohexane"}, {"Citations_Link": "https://scholar.google.com/scholar?cites=11558531414976397373&as_sdt=2005&sciodt=0,5&hl=en&num=20", "Paper_link": "http://www.sciencedirect.com/science/article/pii/S0921509303002508", "authors": ["X Ma", "Y Cai", "X Li", "S Wen "], "Title": "Growth and microstructure of Co-filled carbon nanotubes"}, {"Citations_Link": "https://scholar.google.com/scholar?cites=7906483714146629597&as_sdt=2005&sciodt=0,5&hl=en&num=20", "Paper_link": "http://pubs.acs.org/doi/abs/10.1021/om7003628", "authors": ["VO Nyamori", "NJ Coville "], "Title": "Effect of ferrocene/carbon ratio on the size and shape of carbon nanotubes and microspheres"}, {"Citations_Link": "https://scholar.google.com/scholar?cites=16835608538337805866&as_sdt=2005&sciodt=0,5&hl=en&num=20", "Title": "[CITATION][C] Synthesis of carbon-encapsulated magnetic nanoparticles by spray pyrolysis of iron carbonyl and ethanol", "authors": ["F Yu", "JN Wang", "ZM Sheng", "LF Su "], "Paper_link": null}, {"Citations_Link": "https://scholar.google.com/scholar?cites=10331518367411319482&as_sdt=2005&sciodt=0,5&hl=en&num=20", "Paper_link": "https://books.google.com/books?hl=en&lr=&id=G9fLBQAAQBAJ&oi=fnd&pg=PA37&ots=t6P3DVWRdN&sig=UjvzdUXMIcIic_nRBmivXRm1Bp4", "authors": ["EG Rakov "], "Title": "2 Chemistry of Carbon Nanotubes"}, {"Citations_Link": "https://scholar.google.com/scholar?cites=5121198061365190045&as_sdt=2005&sciodt=0,5&hl=en&num=20", "Paper_link": "http://pubs.acs.org/doi/abs/10.1021/jp062526x", "authors": ["W Ren", "F Li", "HM Cheng "], "Title": "Evidence for, and an understanding of, the initial nucleation of carbon nanotubes produced by a floating catalyst method"}, {"Citations_Link": "https://scholar.google.com/scholar?cites=1664592894305442073&as_sdt=2005&sciodt=0,5&hl=en&num=20", "Paper_link": "http://www.sciencedirect.com/science/article/pii/S0038109803002151", "authors": ["W Qian", "F Wei", "T Liu", "ZW Wang "], "Title": "The formation mechanism of the coaxial carbon\u2013metal nanowires in a chemical vapor deposition process"}, {"Citations_Link": "https://scholar.google.com/scholar?cites=7913282674155722591&as_sdt=2005&sciodt=0,5&hl=en&num=20", "Paper_link": "http://link.springer.com/article/10.1007/s00339-007-4028-3", "authors": ["YA Kasumov", "A Shailos", "II Khodos", "VT Volkov "], "Title": "CVD growth of carbon nanotubes at very low pressure of acetylene"}, {"Citations_Link": "https://scholar.google.com/scholar?cites=833770805417922502&as_sdt=2005&sciodt=0,5&hl=en&num=20", "Paper_link": "http://www.sciencedirect.com/science/article/pii/S0167577X02013915", "authors": ["X Ma", "Y Cai", "N Lun", "Q Ao", "S Li", "F Li", "S Wen "], "Title": "Microstructural features of Co-filled carbon nanotubes"}, {"Citations_Link": "https://scholar.google.com/scholar?cites=12131107813139802087&as_sdt=2005&sciodt=0,5&hl=en&num=20", "Paper_link": "https://www.google.com/patents/US7338648", "authors": ["A Harutyunyan", "BK Pradhan", "PC Eklund "], "Title": "Method for low temperature synthesis of single wall carbon nanotubes"}, {"Citations_Link": "https://scholar.google.com/scholar?cites=9915255815693580337&as_sdt=2005&sciodt=0,5&hl=en&num=20", "Paper_link": "http://www.tandfonline.com/doi/full/10.1088/1468-6996/11/5/054501", "authors": ["UK Gautam", "PMFJ Costa", "Y Bando", "X Fang "], "Title": "Recent developments in inorganically filled carbon nanotubes: successes and challenges"}, {"Citations_Link": "https://scholar.google.com/scholar?cites=10139389070724263439&as_sdt=2005&sciodt=0,5&hl=en&num=20", "Paper_link": "http://www.sciencedirect.com/science/article/pii/S1359645404001740", "authors": ["D Golberg", "Y Bando", "M Mitome", "K Fushimi", "C Tang "], "Title": "Boron nitride nanotubes as nanocrucibles for morphology and phase transformations in encapsulated nanowires of the Mg\u2013O system"}, {"Citations_Link": "https://scholar.google.com/scholar?cites=17825191459987667946&as_sdt=2005&sciodt=0,5&hl=en&num=20", "Paper_link": "http://pubs.rsc.org/en/content/articlehtml/2004/jm/b402936d", "authors": ["TM Keller", "SB Qadri", "CA Little "], "Title": "Carbon nanotube formation in situ during carbonization in shaped bulk solid cobalt nanoparticle compositions"}, {"Citations_Link": "https://scholar.google.com/scholar?cites=7764244400147201929&as_sdt=2005&sciodt=0,5&hl=en&num=20", "Paper_link": "http://www.sciencedirect.com/science/article/pii/S002236970100097X", "authors": ["CC Chen", "CC Yeh", "CH Liang", "CC Lee", "CH Chen "], "Title": "Preparation and characterization of carbon nanotubes encapsulated GaN nanowires"}, {"Citations_Link": "https://scholar.google.com/scholar?cites=681166225118277514&as_sdt=2005&sciodt=0,5&hl=en&num=20", "Paper_link": "http://www.sciencedirect.com/science/article/pii/S174801321400098X", "authors": ["X Mao", "GC Rutledge", "TA Hatton "], "Title": "Nanocarbon-based electrochemical systems for sensing, electrocatalysis, and energy storage"}, {"Citations_Link": "https://scholar.google.com/scholar?cites=4011592561702298201&as_sdt=2005&sciodt=0,5&hl=en&num=20", "Paper_link": "http://physicsonline.ru/PaperLogos/7326/files/Full_text_Russian_version.pdf", "authors": ["  "], "Title": "\u0425\u0438\u043c\u0438\u044f \u0438 \u043f\u0440\u0438\u043c\u0435\u043d\u0435\u043d\u0438\u0435 \u0443\u0433\u043b\u0435\u0440\u043e\u0434\u043d\u044b\u0445 \u043d\u0430\u043d\u043e\u0442\u0440\u0443\u0431\u043e\u043a"}, {"Citations_Link": "https://scholar.google.com/scholar?cites=13400749455538057695&as_sdt=2005&sciodt=0,5&hl=en&num=20", "Paper_link": "http://pubs.acs.org/doi/abs/10.1021/jp010083l", "authors": ["S Liu", "S Boeshore", "A Fernandez "], "Title": "Study of cobalt-filled carbon nanoflasks"}, {"Citations_Link": "https://scholar.google.com/scholar?cites=18382076570023091110&as_sdt=2005&sciodt=0,5&hl=en&num=20", "Paper_link": "http://www.ingentaconnect.com/content/asp/jnn/2012/00000012/00000005/art00120", "authors": ["JH Eum", "SH Kim", "SS Yi", "K Jang "], "Title": "Large-scale synthesis of the controlled-geometry carbon coils by the manipulation of the SF6 gas flow injection time"}, {"Citations_Link": "https://scholar.google.com/scholar?cites=9761822243327594023&as_sdt=2005&sciodt=0,5&hl=en&num=20", "Paper_link": "http://journals.jps.jp/doi/pdf/10.1143/JPSJ.74.742", "authors": ["M Mahmudur Rahman", "M Kisaku", "T Kishi "], "Title": "Electric and magnetic properties of Co-filled carbon nanotube"}, {"Citations_Link": "https://scholar.google.com/scholar?cites=10676012591091758130&as_sdt=2005&sciodt=0,5&hl=en&num=20", "Paper_link": "http://pubs.acs.org/doi/abs/10.1021/cm3006088", "authors": ["S Chatterjee", "MJ Kim", "DN Zakharov", "SM Kim "], "Title": "Syntheses of Boron Nitride Nanotubes from Borazine and Decaborane Molecular Precursors by Catalytic Chemical Vapor Deposition with a Floating Nickel Catalyst"}, {"Citations_Link": "https://scholar.google.com/scholar?cites=9181462887178905819&as_sdt=2005&sciodt=0,5&hl=en&num=20", "Paper_link": "http://www.sciencedirect.com/science/article/pii/S0009261410009772", "authors": ["Y Lei", "R Zhao", "Y Zhan", "F Meng", "J Zhong", "X Yang "], "Title": "Generation of multiwalled carbon nanotubes from iron\u2013phthalocyanine polymer and their novel dielectric properties"}, {"Citations_Link": "https://scholar.google.com/scholar?cites=16969882213645870993&as_sdt=2005&sciodt=0,5&hl=en&num=20", "Paper_link": "http://www.sciencedirect.com/science/article/pii/S0008622305006895", "authors": ["T Hayashi", "H Muramatsu", "YA Kim", "H Kajitani", "S Imai "], "Title": "TEM image simulation study of small carbon nanotubes and carbon nanowire"}, {"Citations_Link": "https://scholar.google.com/scholar?cites=10556590648981023018&as_sdt=2005&sciodt=0,5&hl=en&num=20", "Paper_link": "http://www.tandfonline.com/doi/abs/10.1081/E-ENN2-120009099", "authors": ["Y Lin", "W Yantasee", "F Lu", "J Wang", "M Musameh", "Y Tu "], "Title": "Dekker Encyclopedia of Nanoscience and Nanotechnology"}, {"Citations_Link": "https://scholar.google.com/scholar?cites=7455728673134655977&as_sdt=2005&sciodt=0,5&hl=en&num=20", "Paper_link": "http://www.sciencedirect.com/science/article/pii/S0254058408002289", "authors": ["D Yuan", "Y Liu", "Y Xiao", "L Chen "], "Title": "Preparation and characterization of Z-shaped carbon nanotubes via decomposing magnesium acetate"}, {"Citations_Link": "https://scholar.google.com/scholar?cites=14892609265770438384&as_sdt=2005&sciodt=0,5&hl=en&num=20", "Paper_link": "https://www.researchgate.net/profile/Woo_Jung/publication/238483998_Characterization_of_Graphene_Sheets_Formed_by_the_Reaction_of_Carbon_Monoxide_with_Aluminum_Sulfide/links/00b49533413455329e000000.pdf", "authors": ["I Yoon", "CD Kim", "BK Min", "YK Kim", "B Kim "], "Title": "Characterization of graphene sheets formed by the reaction of carbon monoxide with aluminum sulfide"}, {"Citations_Link": "https://scholar.google.com/scholar?cites=3731058933148010836&as_sdt=2005&sciodt=0,5&hl=en&num=20", "Paper_link": "http://www.sciencedirect.com/science/article/pii/S0169433212023021", "authors": ["J Wang", "Z Dong", "J Huang", "J Li", "X Jin", "J Niu", "J Sun "], "Title": "Filling carbon nanotubes with Ni\u2013Fe alloys via methylbenzene-oriented constant current electrodeposition for hydrazine electrocatalysis"}, {"Citations_Link": "https://scholar.google.com/scholar?cites=6906486541904088633&as_sdt=2005&sciodt=0,5&hl=en&num=20", "Paper_link": "http://pubs.acs.org/doi/abs/10.1021/ic300767h", "authors": ["C Daz", "ML Valenzuela", "V Lavayen "], "Title": "Layered graphitic carbon host formation during liquid-free solid state growth of metal pyrophosphates"}, {"Citations_Link": "https://scholar.google.com/scholar?cites=1319619434826014458&as_sdt=2005&sciodt=0,5&hl=en&num=20", "Paper_link": "http://www.eng.uwo.ca/people/jherrera/journal9.pdf", "authors": ["DE Resasco", "JE Herrera "], "Title": "Structural characterization of single-walled carbon nanotubes"}, {"Citations_Link": "https://scholar.google.com/scholar?cites=3234742488347705932&as_sdt=2005&sciodt=0,5&hl=en&num=20", "Paper_link": "http://onlinelibrary.wiley.com/doi/10.1002/cvde.200506449/abstract", "authors": ["GA Domrachev", "AM Obedkov "], "Title": "MOCVD Synthesis of Germanium Filled \u201cDiamondlike\u201d Carbon Nanotubes and Microtubes from Organogermanium Precursors and Their Field\u2010Emission Properties"}, {"Citations_Link": "https://scholar.google.com/scholar?cites=12665556285242654336&as_sdt=2005&sciodt=0,5&hl=en&num=20", "Paper_link": "http://scitation.aip.org/content/aip/journal/jap/108/6/10.1063/1.3474650", "authors": ["SN Mohammad "], "Title": "General hypothesis and shell model for the synthesis of semiconductor nanotubes, including carbon nanotubes"}, {"Citations_Link": "https://scholar.google.com/scholar?cites=16641001806200888212&as_sdt=2005&sciodt=0,5&hl=en&num=20", "Paper_link": "https://www.researchgate.net/profile/Nancy_Monteiro-Riviere2/publication/6377849_Biological_Properties_of_Carbon_Nanotubes/links/55de194408ae79830bb584f1.pdf", "authors": ["W Wei", "A Sethuraman", "C Jin "], "Title": "Biological Properties of Carbon Nanotubes"}, {"Citations_Link": "https://scholar.google.com/scholar?cites=15431307160464625769&as_sdt=2005&sciodt=0,5&hl=en&num=20", "Paper_link": "http://onlinelibrary.wiley.com/doi/10.1002/0471695432.ch3/summary", "authors": ["AD Pomogailo", "AS Rozenberg "], "Title": "Controlled Pyrolysis of Metal\u2010Containing Precursors as a Way for Synthesis of Metallopolymer Nanocomposites"}, {"Citations_Link": "https://scholar.google.com/scholar?cites=2594723908425061423&as_sdt=2005&sciodt=0,5&hl=en&num=20", "Paper_link": "http://www.tandfonline.com/doi/abs/10.1080/17458080701745658", "authors": ["AS Afolabi", "AS Abdulkareem "], "Title": "Synthesis of carbon nanotubes and nanoballs by swirled floating catalyst chemical vapour deposition method"}, {"Citations_Link": "https://scholar.google.com/scholar?cites=15540734612838695055&as_sdt=2005&sciodt=0,5&hl=en&num=20", "Paper_link": "http://www.sciencedirect.com/science/article/pii/S0025540815301033", "authors": ["AT Lawal "], "Title": "Synthesis and utilization of carbon nanotubes for fabrication of electrochemical biosensors"}, {"Citations_Link": "https://scholar.google.com/scholar?cites=11683131950855887834&as_sdt=2005&sciodt=0,5&hl=en&num=20", "Paper_link": "http://onlinelibrary.wiley.com/doi/10.1002/adma.200304690/full", "authors": ["RK Rana", "XN Xu", "Y Yeshurun "], "Title": "Fabrication of the MgCxCo3 ternary phase encapsulated in carbon nanoflasks"}, {"Citations_Link": "https://scholar.google.com/scholar?cites=4184815009727858463&as_sdt=2005&sciodt=0,5&hl=en&num=20", "Paper_link": "http://link.springer.com/article/10.1007/s10853-005-0489-y", "authors": ["Y Mi", "Y Liu", "D Yuan", "J Zhang", "Y Xiao "], "Title": "Synthesis of carbon nanotubes via toluene-thermal reduction process at moderate temperature"}, {"Citations_Link": "https://scholar.google.com/scholar?cites=1731529635593207811&as_sdt=2005&sciodt=0,5&hl=en&num=20", "Paper_link": "https://books.google.com/books?hl=en&lr=&id=BkbxYHz__dkC&oi=fnd&pg=PA15&ots=ZuEFEDj2qc&sig=Ztqq3senyk1slUjsdXrO8cRdlzk", "authors": ["A Govindaraj", "CNR Rao "], "Title": "Synthesis, growth mechanism and processing of carbon nanotubes"}, {"Citations_Link": "https://scholar.google.com/scholar?cites=15985758508840713940&as_sdt=2005&sciodt=0,5&hl=en&num=20", "Paper_link": "http://www.sciencedirect.com/science/article/pii/S0925963505002578", "authors": ["Y Huh", "MLH Green", "JY Lee", "CJ Lee "], "Title": "Vapor phase deposition of carbon nanotubes using tungsten-organic source and acetylene"}, {"Citations_Link": "https://scholar.google.com/scholar?cites=3726512996677636684&as_sdt=2005&sciodt=0,5&hl=en&num=20", "Paper_link": "http://www.airitilibrary.com/Publication/alDetailedMesh?docid=10078827-200709-22-3-271-282-a", "authors": ["       "], "Title": "\u78b3\u7eb3\u7c73\u7ba1\u9635\u5217\u7814\u7a76\u8fdb\u5c55"}, {"Citations_Link": "https://scholar.google.com/scholar?cites=10103804534377769187&as_sdt=2005&sciodt=0,5&hl=en&num=20", "Paper_link": "http://carbonlett.org/Upload/files/CARBONLETT/120-141.pdf", "authors": ["YH Lee", "DJ Bae", "KH An", "SC Lim", "JM Moon", "YC Choi "], "Title": "Synthesis and Applications of Carbon Nanotubes"}, {"Citations_Link": "https://scholar.google.com/scholar?cites=4601385342760522013&as_sdt=2005&sciodt=0,5&hl=en&num=20", "Paper_link": "http://link.springer.com/chapter/10.1007/3-540-26523-6_5", "authors": ["AD Pomogailo", "VN Kestelman "], "Title": "Chemical Methods of Metal-Polymer Nanocomposite Production"}, {"Citations_Link": "https://scholar.google.com/scholar?cites=1468649507715084740&as_sdt=2005&sciodt=0,5&hl=en&num=20", "Paper_link": "http://www.sciencedirect.com/science/article/pii/S089684461500114X", "authors": ["E Garrido", "C Aymonier", "L Roiban", "O Ersen "], "Title": "Noble metals supported on carbon nanotubes using supercritical fluids for the preparation of composite materials: A look at the interface"}, {"Citations_Link": "https://scholar.google.com/scholar?cites=11567527108850210251&as_sdt=2005&sciodt=0,5&hl=en&num=20", "Paper_link": "http://www.sciencedirect.com/science/article/pii/S0254058411009308", "authors": ["EC Linganiso", "G Chimowa", "PJ Franklyn "], "Title": "The effect of tube filling on the electronic properties of Fe filled carbon nanotubes"}, {"Citations_Link": "https://scholar.google.com/scholar?cites=5190802407452170629&as_sdt=2005&sciodt=0,5&hl=en&num=20", "Paper_link": "http://www.sciencedirect.com/science/article/pii/S0008622315001268", "authors": ["Z Ruan", "W Rong", "Q Li", "Z Li "], "Title": "Oxygen as the growth enhancer of carbon nanotubes in solid-state pyrolysis of organometallic precursors"}, {"Citations_Link": "https://scholar.google.com/scholar?cites=8898686007147317293&as_sdt=2005&sciodt=0,5&hl=en&num=20", "Paper_link": "http://link.springer.com/chapter/10.1007/1-85233-849-0_5", "authors": ["L Dai "], "Title": "Carbon Nanotubes"}, {"Citations_Link": "https://scholar.google.com/scholar?cites=11367862555847983439&as_sdt=2005&sciodt=0,5&hl=en&num=20", "Paper_link": "http://www.ncbi.nlm.nih.gov/pmc/articles/PMC4233916/", "authors": ["G Kawamura", "H Muto", "A Matsuda "], "Title": "Hard template synthesis of metal nanowires"}, {"Citations_Link": "https://scholar.google.com/scholar?cites=3419406979264743005&as_sdt=2005&sciodt=0,5&hl=en&num=20", "Paper_link": "http://link.springer.com/article/10.1007/BF03353616", "authors": ["SK Srivastava", "VD Vankar", "V Kumar "], "Title": "Effect of hydrogen plasma treatment on the growth and microstructures of multiwalled carbon nanotubes"}, {"Citations_Link": "https://scholar.google.com/scholar?cites=2380469835451810519&as_sdt=2005&sciodt=0,5&hl=en&num=20", "Paper_link": "http://www.osti.gov/scitech/biblio/15016094", "authors": ["Y Lin", "X Ye", "CM Wai", "JA Schwarz", "KP C Contescu "], "Title": "Nanostructured materials synthesized in supercritical fluid"}, {"Citations_Link": "https://scholar.google.com/scholar?cites=4318526511690332340&as_sdt=2005&sciodt=0,5&hl=en&num=20", "Paper_link": "http://www.cnki.com.cn/Article/CJFDTotal-JBXK201306002.htm", "authors": ["     "], "Title": "\u78b3\u7eb3\u7c73\u7ba1\u7684\u5b8f\u91cf\u5236\u5907\u53ca\u4ea7\u4e1a\u5316"}, {"Citations_Link": "https://scholar.google.com/scholar?cites=12817841392927392914&as_sdt=2005&sciodt=0,5&hl=en&num=20", "Paper_link": "http://www.ingentaconnect.com/content/asp/jnn/2012/00000012/00000007/art00157", "authors": ["YC Jeon", "SH Kim "], "Title": "Formation of the Geometrically Controlled Carbon Coils by Manipulating the Additive Gas (SF6) Flow Rate"}, {"Citations_Link": "https://scholar.google.com/scholar?cites=3586775305290048339&as_sdt=2005&sciodt=0,5&hl=en&num=20", "Paper_link": "http://link.springer.com/chapter/10.1007/978-1-4614-0926-7_2", "authors": ["M Nosonovsky", "PK Rohatgi "], "Title": "Thermodynamic principles of self-healing metallic materials"}, {"Citations_Link": "https://scholar.google.com/scholar?cites=16250195612495269185&as_sdt=2005&sciodt=0,5&hl=en&num=20", "Paper_link": "http://www.airitilibrary.com/Publication/alDetailedMesh?docid=10014381-200807-2008-7-83-87-a", "authors": ["     "], "Title": "\u7eb3\u7c73\u7535\u7f06\u6750\u6599\u7684\u7814\u7a76\u8fdb\u5c55"}, {"Citations_Link": "https://scholar.google.com/scholar?cites=1838816663851359532&as_sdt=2005&sciodt=0,5&hl=en&num=20", "Paper_link": "http://link.springer.com/article/10.1007/s00339-004-2988-0", "authors": ["Y Huh", "JY Lee", "SK Choi", "CJ Lee "], "Title": "Catalytic production of carbon nanotubes by vapor phase growth method using tungsten-containing organic compound"}, {"Citations_Link": "https://scholar.google.com/scholar?cites=10669599814891603069&as_sdt=2005&sciodt=0,5&hl=en&num=20", "Title": "[CITATION][C] HiPco Process for Single-Wall Carbon Nanotube Production", "authors": ["P Nikolaev "], "Paper_link": null}, {"Citations_Link": "https://scholar.google.com/scholar?cites=13553648587475643102&as_sdt=2005&sciodt=0,5&hl=en&num=20", "Title": "[CITATION][C] Filling of Carbon Nanotubes", "authors": ["PK Tyagi", "MK Singh", "DS Misra "], "Paper_link": null}, {"Citations_Link": "https://scholar.google.com/scholar?cites=2176888749162077636&as_sdt=2005&sciodt=0,5&hl=en&num=20", "Paper_link": "https://books.google.com/books?hl=en&lr=&id=CZwi-7JFhOAC&oi=fnd&pg=PA443&ots=A84VaDbp12&sig=_pvGwV7wD5ulYI3ZM6X7E3FrJ5s", "authors": ["DE Resasco", "KJ Klabunde "], "Title": "Carbon nanotubes and related structures"}, {"Citations_Link": "https://scholar.google.com/scholar?cites=2388797689806534281&as_sdt=2005&sciodt=0,5&hl=en&num=20", "Paper_link": "https://www.google.com/patents/US8834827", "authors": ["B Simard", "CT Kingston", "S Denommee", "G Soucy "], "Title": "Method and apparatus for the continuous production and functionalization of single-walled carbon nanotubes using a high frequency plasma torch"}, {"Citations_Link": "https://scholar.google.com/scholar?cites=3806049998171412323&as_sdt=2005&sciodt=0,5&hl=en&num=20", "Paper_link": "http://pubs.rsc.org/en/content/articlehtml/2013/nr/c3nr02291a", "authors": ["F Cao", "Y Ding", "L Chen", "C Zhang "], "Title": "Improvement of crystallization of borazine-derived boron nitride using small amounts of Fe or Ni nanoparticles"}, {"Citations_Link": "https://scholar.google.com/scholar?cites=6147642038948349252&as_sdt=2005&sciodt=0,5&hl=en&num=20", "Paper_link": "https://urresearch.rochester.edu/fileDownloadForInstitutionalItem.action?itemId=5535&itemFileId=8540", "authors": ["HN Pedrosa "], "Title": "The optical properties of single-walled carbon nanotubes"}, {"Citations_Link": "https://scholar.google.com/scholar?q=related:qpSEHpXVYeMJ:scholar.google.com/&hl=en&num=20&as_sdt=0,5&sciodt=0,5", "Paper_link": "http://www.osti.gov/scitech/biblio/1080152", "authors": ["Y Lin", "X Ye", "CM Wai "], "Title": "Nanostructured Materials: Symthesis in Supercritical Fluids"}, {"Citations_Link": "https://scholar.google.com/scholar?q=related:X0HKKG-pNecJ:scholar.google.com/&hl=en&num=20&as_sdt=0,5&sciodt=0,5", "Paper_link": "http://uknowledge.uky.edu/gradschool_theses/459/", "authors": ["LD Cherukuri "], "Title": "Catalytic Growth of Structured Carbon Via the Decomposition of Halogenated Reactants Over Supported Nickel"}, {"Citations_Link": "https://scholar.google.com/scholar?q=related:310qQjDdsW4J:scholar.google.com/&hl=en&num=20&as_sdt=0,5&sciodt=0,5", "Title": "[CITATION][C] Effect of the flow rate and the injection time of SF6 on the formation of the geometrically controlled carbon coils", "authors": ["YC Jeon", "SH Kim"], "Paper_link": null}, {"Citations_Link": "https://scholar.google.com/scholar?q=related:hqiZYt8Q9vUJ:scholar.google.com/&hl=en&num=20&as_sdt=0,5&sciodt=0,5", "Paper_link": "https://inis.iaea.org/search/search.aspx?orig_q=RN:44036305", "authors": ["Y Wu", "J Qiu", "H Kim", "Y Hwang", "Z Wang "], "Title": "Synthesis of carbon nanotube-Cu x O (x= 8, 64) nanocrystal composites"}, {"Citations_Link": "https://scholar.google.com/scholar?q=related:mfNDcYXEab4J:scholar.google.com/&hl=en&num=20&as_sdt=0,5&sciodt=0,5", "Title": "[CITATION][C] One-Dimensional Nanomaterials from Organics", "authors": ["KF Cai "], "Paper_link": null}, {"Citations_Link": "https://scholar.google.com/scholar?q=related:NwHOeNsrny4J:scholar.google.com/&hl=en&num=20&as_sdt=0,5&sciodt=0,5", "Paper_link": "http://onlinelibrary.wiley.com/doi/10.1002/chem.201504444/full", "authors": ["S Husmann", "AJG Zarbin "], "Title": "Design of a Prussian Blue Analogue/Carbon Nanotube Thin\u2010Film Nanocomposite: Tailored Precursor Preparation, Synthesis, Characterization, and Application"}, {"Citations_Link": "https://scholar.google.com/scholar?q=related:O34shTUwptQJ:scholar.google.com/&hl=en&num=20&as_sdt=0,5&sciodt=0,5", "Paper_link": "https://books.google.com/books?hl=en&lr=&id=b_7FCgAAQBAJ&oi=fnd&pg=PA445&ots=Z07NsOjX6R&sig=8k4_vdUXbf-EeWAxnSc-CcKrIxE", "authors": ["CNR RAO", "A GOVINDARAJ "], "Title": "Organometallic Precursors"}, {"Citations_Link": "https://scholar.google.com/scholar?q=related:Cw4ujKCFjsgJ:scholar.google.com/&hl=en&num=20&as_sdt=0,5&sciodt=0,5", "Paper_link": "https://books.google.com/books?hl=en&lr=&id=cRTJCgAAQBAJ&oi=fnd&pg=PA271&ots=KG32MgqkUz&sig=O4-rtd4uCXvqGYqEvS6ziFvXNrg", "authors": ["JP Zhang", "AK Cheetham "], "Title": "B\u2013C\u2013N, CN and BN nanotubes produced by the pyrolysis of precursor molecules over Co catalysts"}, {"Citations_Link": "https://scholar.google.com/scholar?q=related:uKU3na7VDMcJ:scholar.google.com/&hl=en&num=20&as_sdt=0,5&sciodt=0,5", "Paper_link": "https://etd.ohiolink.edu/!etd.send_file?accession=akron1131983430&disposition=attachment", "authors": ["V Bajpai "], "Title": "SYNTHESES, CHARACTERIZATION AND APPLICATIONS OF MICRO-/NANO-STRUCTURED CONDUCTING POLYMERS AND CARBON NANOTUBES"}, {"Citations_Link": "https://scholar.google.com/scholar?q=related:Qr2jrW7qfeIJ:scholar.google.com/&hl=en&num=20&as_sdt=0,5&sciodt=0,5", "Title": "[CITATION][C] A Selection of CNR Rao's Publications (1994\u20132003)", "authors": ["R Sen", "BC Satishkumar", "A Govindaraj", "KR Harikumar "], "Paper_link": null}, {"Citations_Link": "https://scholar.google.com/scholar?q=related:lUyBvDbUKAwJ:scholar.google.com/&hl=en&num=20&as_sdt=0,5&sciodt=0,5", "Paper_link": "http://ecst.ecsdl.org/content/13/14/43.short", "authors": ["DS Yuan", "YL Liu", "L Chen "], "Title": "Preparation of the Capsule-like Carbon Tubes via a Facile Solvothermal Route"}, {"Citations_Link": "https://scholar.google.com/scholar?q=related:f3rIwvliaRMJ:scholar.google.com/&hl=en&num=20&as_sdt=0,5&sciodt=0,5", "Title": "[CITATION][C] Solid-State Synthesis of Carbon Nanotubes", "authors": ["HC Zeng "], "Paper_link": null}, {"Citations_Link": "https://scholar.google.com/scholar?q=related:3NCYzbBrvT8J:scholar.google.com/&hl=en&num=20&as_sdt=0,5&sciodt=0,5", "Paper_link": "http://search.ebscohost.com/login.aspx?direct=true&profile=ehost&scope=site&authtype=crawler&jrnl=16629795&AN=112753438&h=arBctj%2BwZ4jE4ODvxm9ZRE%2B43WatTW88%2FgYGGaGpTjL1RhLqzYIhi3JlAsQH3%2FD6kxr5jj8I7KvgeZ6ApbuKNA%3D%3D&crl=c", "authors": ["JK Lee", "SH Kim "], "Title": "Effect of the SF 6 Flow Injection Time on the Formation of the Carbon Coils."}, {"Citations_Link": "https://scholar.google.com/scholar?q=related:15iA2d3KnZ0J:scholar.google.com/&hl=en&num=20&as_sdt=0,5&sciodt=0,5", "Title": "[CITATION][C] Selected Research Papers of CNR Rao", "authors": ["CNR Rao "], "Paper_link": null}, {"Citations_Link": "https://scholar.google.com/scholar?q=related:MqeU4fSXYFAJ:scholar.google.com/&hl=en&num=20&as_sdt=0,5&sciodt=0,5", "Title": "[CITATION][C] A Selection of CNR Rao's Publications (1994\u20132003)", "authors": ["CNR Rao", "GU Kulkarni", "PJ Thomas", "PP Edwards "], "Paper_link": null}, {"Citations_Link": "https://scholar.google.com/scholar?q=related:AZqr7Y2lMK0J:scholar.google.com/&hl=en&num=20&as_sdt=0,5&sciodt=0,5", "Paper_link": "http://ujdigispace.uj.ac.za/handle/10210/2536", "authors": ["MJB Cele "], "Title": "in loving memory of my father"}, {"Citations_Link": "https://scholar.google.com/scholar?q=related:QiuJ75RDHAUJ:scholar.google.com/&hl=en&num=20&as_sdt=0,5&sciodt=0,5", "Paper_link": "http://www.scientific.net/AMR.11-12.587", "authors": ["X Li", "DL Zhao", "ZM Shen "], "Title": "Microstructure and Formation Mechanism of Carbon Nanotubes Filled with Metallic Silver Nanowires"}, {"Citations_Link": "https://scholar.google.com/scholar?q=related:omJr-0KZaxYJ:scholar.google.com/&hl=en&num=20&as_sdt=0,5&sciodt=0,5", "Paper_link": "http://pubs.rsc.org/en/content/articlehtml/2016/cc/c5cc09219a", "authors": ["Z Ruan", "Y Zhang", "J Tu", "J Qin", "Q Li", "Z Li "], "Title": "Dramatically enhancing the yield of carbon nanotubes by simply adding oxygen-containing molecules in solid-state synthesis"}, {"Citations_Link": "https://scholar.google.com/scholar?q=related:xMvxc3Dg1ZoJ:scholar.google.com/&hl=en&num=20&as_sdt=0,5&sciodt=0,5", "Paper_link": "http://acervodigital.ufpr.br/handle/1884/41284", "authors": ["S Husmann "], "Title": "Materiais multifuncionais baseados em nanocomp\u00f3sitos do tipo nanotubos de carbono e an\u00e1logos de azul da Pr\u00fassia"}, {"Citations_Link": "https://scholar.google.com/scholar?q=related:mb-RrC9RbYYJ:scholar.google.com/&hl=en&num=20&as_sdt=0,5&sciodt=0,5", "Paper_link": "http://www.cheric.org/research/tech/periodicals/view.php?seq=500099", "authors": ["Y Huh", "JY Lee", "SK Choi", "CJ Lee "], "Title": "Synthesis of multiwalled carbon nanotubes using C14H10O7W catalyst"}, {"Citations_Link": "https://scholar.google.com/scholar?q=related:L0hy0yLoP2MJ:scholar.google.com/&hl=en&num=20&as_sdt=0,5&sciodt=0,5", "Paper_link": "http://cyberleninka.ru/article/n/osobennosti-upravlyaemoy-tehnologii-uglerodnyh-nanotrubok", "authors": [" ", "  "], "Title": "\u041e\u0441\u043e\u0431\u0435\u043d\u043d\u043e\u0441\u0442\u0438 \u0443\u043f\u0440\u0430\u0432\u043b\u044f\u0435\u043c\u043e\u0439 \u0442\u0435\u0445\u043d\u043e\u043b\u043e\u0433\u0438\u0438 \u0443\u0433\u043b\u0435\u0440\u043e\u0434\u043d\u044b\u0445 \u043d\u0430\u043d\u043e\u0442\u0440\u0443\u0431\u043e\u043a"}], "title": "Metal-filled and hollow carbon nanotubes obtained by the decomposition of metal-containing free precursor molecules", "authors": ["R Sen", "A Govindaraj", "CNR Rao"], "paper_link": "https://scholar.google.com/citations?view_op=view_citation&hl=en&user=Zs9227oAAAAJ&cstart=62&pagesize=100&citation_for_view=Zs9227oAAAAJ:a0OBvERweLwC"}