{"citations": [{"Paper_link": "http://scitation.aip.org/content/aip/journal/jap/89/11/10.1063/1.1359460", "Title": "Metallization of magnetite (Fe3O4) under high pressure", "authors": ["S Todo", "N Takeshita", "T Kanehara", "T Mori "], "Citations_Link": "https://scholar.google.com/scholar?cites=17027326739203743540&as_sdt=2005&sciodt=0,5&hl=en&num=20"}, {"Paper_link": "http://journals.aps.org/prb/abstract/10.1103/PhysRevB.48.14063", "Title": "Barely metallic states with enhanced carrier mass in Y 1\u2212 x Ca x TiO 3", "authors": ["Y Tokura", "Y Taguchi", "Y Moritomo", "K Kumagai", "T Suzuki "], "Citations_Link": "https://scholar.google.com/scholar?cites=16756287740238581832&as_sdt=2005&sciodt=0,5&hl=en&num=20"}, {"Paper_link": "http://journals.aps.org/prb/abstract/10.1103/PhysRevB.72.035131", "Title": "Terahertz conductivity at the Verwey transition in magnetite", "authors": ["A Pimenov", "S Tachos", "T Rudolf", "A Loidl", "D Schrupp "], "Citations_Link": "https://scholar.google.com/scholar?cites=16943630289575891751&as_sdt=2005&sciodt=0,5&hl=en&num=20"}, {"Paper_link": "http://journals.aps.org/prb/abstract/10.1103/PhysRevB.71.155103", "Title": "EXAFS spectroscopic analysis of the Verwey transition in Fe 3 O 4.", "authors": ["G Subas", "J Garca", "J Blasco "], "Citations_Link": "https://scholar.google.com/scholar?cites=16960103803197417996&as_sdt=2005&sciodt=0,5&hl=en&num=20"}, {"Paper_link": "http://journals.jps.jp/doi/pdf/10.1143/JPSJ.61.1867", "Title": "Metal-Insulator Transition with Oxygen Content in CaVO3-y", "authors": ["F Iga", "Y Nishihara "], "Citations_Link": "https://scholar.google.com/scholar?cites=8330017235357592131&as_sdt=2005&sciodt=0,5&hl=en&num=20"}, {"Paper_link": "http://journals.aps.org/prb/abstract/10.1103/PhysRevB.53.R7584", "Title": "Electronic structure and the metal-insulator transition in Ni S 2\u2212 x Se x", "authors": ["AY Matsuura", "ZX Shen", "DS Dessau", "CH Park", "T Thio "], "Citations_Link": "https://scholar.google.com/scholar?cites=15691151652666749089&as_sdt=2005&sciodt=0,5&hl=en&num=20"}, {"Paper_link": "http://www.sciencedirect.com/science/article/pii/S0921452601015253", "Title": "Metallization of magnetite at high pressures", "authors": ["N Mri", "S Todo", "N Takeshita", "T Mori "], "Citations_Link": "https://scholar.google.com/scholar?cites=7134203660622563950&as_sdt=2005&sciodt=0,5&hl=en&num=20"}, {"Paper_link": "http://www.sciencedirect.com/science/article/pii/0022369792901524", "Title": "Fillingness dependence of electronic structures in strongly correlated electron systems: Titanates and vanadates", "authors": ["Y Tokura "], "Citations_Link": "https://scholar.google.com/scholar?cites=8989879790352403708&as_sdt=2005&sciodt=0,5&hl=en&num=20"}, {"Paper_link": "http://journals.aps.org/prb/abstract/10.1103/PhysRevB.55.9514", "Title": "Electronic-correlation effects in the x-ray-photoemission spectra of NiS 2", "authors": ["L Sangaletti", "F Parmigiani", "T Thio", "JW Bennett "], "Citations_Link": "https://scholar.google.com/scholar?cites=3396242615849005541&as_sdt=2005&sciodt=0,5&hl=en&num=20"}, {"Paper_link": "http://iopscience.iop.org/article/10.1088/0953-8984/12/8A/321/meta", "Title": "Carrier mobility in liquid semiconductors", "authors": ["JE Enderby", "AC Barnes "], "Citations_Link": "https://scholar.google.com/scholar?cites=477432650493162293&as_sdt=2005&sciodt=0,5&hl=en&num=20"}, {"Paper_link": "http://www.sciencedirect.com/science/article/pii/S0921510799000434", "Title": "Charge ordering in organic conductors and transition metal oxides", "authors": ["H Seo", "H Fukuyama "], "Citations_Link": "https://scholar.google.com/scholar?cites=11847623150152100768&as_sdt=2005&sciodt=0,5&hl=en&num=20"}, {"Paper_link": "https://books.google.com/books?hl=en&lr=&id=cRTJCgAAQBAJ&oi=fnd&pg=PA175&ots=KG32NjqeWB&sig=e9x_QVI6adSglLo_C6Ib0qLRAZk", "Title": "Charge, Spin, and Orbital Ordering in the Perovskite Manganates, LnI-xA. MnO3", "authors": ["CNR Rao "], "Citations_Link": "https://scholar.google.com/scholar?q=related:2xgzsnJdnMgJ:scholar.google.com/&hl=en&num=20&as_sdt=0,5&sciodt=0,5"}], "paper_link": "https://scholar.google.com/citations?view_op=view_citation&hl=en&user=Zs9227oAAAAJ&cstart=1159&pagesize=100&citation_for_view=Zs9227oAAAAJ:ZIQyR8VWHtoC", "authors": ["JM Honig", "PP Edwards", "CRN Rao"], "title": "The Metallic and Non-Metallic States of Matter", "publication": "Taylor & Francis, London, 1985"}