{"citations": [{"Paper_link": "http://www.sciencedirect.com/science/article/pii/S0261219416300709", "Title": "Monitoring of insecticide resistance in Diaphorina citri Kuwayama (Hemiptera: Psyllidae) from citrus groves of Punjab, Pakistan", "authors": ["A Naeem", "S Freed", "FL Jin", "M Akmal", "M Mehmood "], "Citations_Link": "https://scholar.google.com/scholar?q=related:1BT3dUxMsUgJ:scholar.google.com/&hl=en&num=20&as_sdt=0,5&sciodt=0,5"}], "paper_link": "https://scholar.google.com/citations?view_op=view_citation&hl=en&user=Zs9227oAAAAJ&cstart=1959&pagesize=100&citation_for_view=Zs9227oAAAAJ:AU_EAA-G7qsC", "authors": ["CN Rao", "VJ Shivankar", "S Deole", "KJ David", "VN Dhengre"], "title": "Insecticide Resistance in Field Populations of Asian Citrus Psyllid, Diaphorina citri Kuwayama (Hemiptera: Psyllidae)", "publication": "Pesticide Research Journal 26 (1), 42-47, 2014"}