{"citations": [{"Paper_link": "http://www.sciencedirect.com/science/article/pii/003810989190320U", "Title": "Superconductivity and possible carrier localization in YBa 2 Cu 3\u2212 x ZinxO 7\u2212 y", "authors": ["SK Agarwal", "R Suryanarayanan", "O Gorochov "], "Citations_Link": "https://scholar.google.com/scholar?cites=15038651001537554629&as_sdt=2005&sciodt=0,5&hl=en&num=20"}], "paper_link": "https://scholar.google.com/citations?view_op=view_citation&hl=en&user=Zs9227oAAAAJ&cstart=1959&pagesize=100&citation_for_view=Zs9227oAAAAJ:CLQ-NLsb8zAC", "authors": ["CVN RAO", "SK Agarwal", "AV Narlikar", "MP Das"], "title": "LOW TEMPERATURE RESISTANCE BEHAVIOR AND SUPERCONDUCTIVITY OF La\u2013Sr\u2013Cu\u2013O SYSTEM: ROLE OF ALTERED Cu\u2013VALENCE AND O\u2013CONTENT", "publication": "Modern Physics Letters B 4 (05), 357-362, 1990"}