{"citations": [{"Paper_link": "http://pubs.acs.org/doi/abs/10.1021/ar00112a003", "Title": "Intergrowth structures: the chemistry of solid-solid interfaces", "authors": ["CNR Rao", "JM Thomas "], "Citations_Link": "https://scholar.google.com/scholar?cites=1331283366115625363&as_sdt=2005&sciodt=0,5&hl=en&num=20"}, {"Paper_link": "http://www.sciencedirect.com/science/article/pii/0263436895000046", "Title": "The crystal chemistry of the higher tungsten oxides", "authors": ["RJD Tilley "], "Citations_Link": "https://scholar.google.com/scholar?cites=7911656699869132299&as_sdt=2005&sciodt=0,5&hl=en&num=20"}, {"Paper_link": "http://www.sciencedirect.com/science/article/pii/S0022459600988662", "Title": "High-Pressure Tungsten Bronzes, RE x WO 3 with RE= La and Nd, Studied by X-Ray Diffraction and Electron Microscopy", "authors": ["C Grenthe", "M Sundberg", "VP Filonenko "], "Citations_Link": "https://scholar.google.com/scholar?cites=14362385074002853813&as_sdt=2005&sciodt=0,5&hl=en&num=20"}, {"Paper_link": "http://www.sciencedirect.com/science/article/pii/S0022459699984141", "Title": "Intergrowth Tungsten Bronze Structures of Pr x WO 3, Formed at 50 kbar: An HRTEM Study", "authors": ["ND Zakharov", "P Werner", "IP Zibrov", "VP Filonenko "], "Citations_Link": "https://scholar.google.com/scholar?cites=4039587303708903006&as_sdt=2005&sciodt=0,5&hl=en&num=20"}, {"Paper_link": "http://link.springer.com/chapter/10.1007/978-94-009-4582-1_26", "Title": "Transition metal bronzes: properties and reactivity", "authors": ["PA Sermon "], "Citations_Link": "https://scholar.google.com/scholar?cites=14098000901655640328&as_sdt=2005&sciodt=0,5&hl=en&num=20"}], "paper_link": "https://scholar.google.com/citations?view_op=view_citation&hl=en&user=Zs9227oAAAAJ&cstart=1559&pagesize=100&citation_for_view=Zs9227oAAAAJ:8O4vDxvErlEC", "authors": ["DA Jefferson", "MK Uppal", "DJ Smith", "J Gopalakrishnan", "A Ramanan", "..."], "title": "Intergrowth tungsten bronzes of bismuth", "publication": "Materials research bulletin 19 (4), 535-537, 1984"}