{"citations": null, "paper_link": "https://scholar.google.com/citations?view_op=view_citation&hl=en&user=Zs9227oAAAAJ&cstart=2559&pagesize=100&citation_for_view=Zs9227oAAAAJ:0KZCP5UExFUC", "authors": ["CN Rao", "KC Rajanna", "YU Devi", "VS Rao", "PK Saiprakash"], "title": "Thermodynamic parameters and stability constants of some tervalent lanthanide complexes of 1-(3-aryl-5-hydroxy 4-isoxazolylazo) 4-sulphonic acids", "publication": "Proceedings of the Indian Academy of Sciences-Chemical Sciences 100 (4), 329-335, 1988"}