{"citations": [{"Paper_link": "http://journals.aps.org/prb/abstract/10.1103/PhysRevB.70.184437", "Title": "Metal-insulator transition and ferromagnetism phenomena in La 0.7 Ce 0.3 MnO 3 thin films: Formation of Ce-rich nanoclusters", "authors": ["T Yanagida", "T Kanki", "B Vilquin", "H Tanaka", "T Kawai "], "Citations_Link": "https://scholar.google.com/scholar?cites=8614640523398754557&as_sdt=2005&sciodt=0,5&hl=en&num=20"}, {"Paper_link": "http://www.sciencedirect.com/science/article/pii/S1463018402000461", "Title": "Influence of cation vacancies on structural and magnetic properties of La 1\u2212 xMnO 3+ \u03b4 nanopowders", "authors": ["G Dezanneau", "O Isnard", "H Roussel", "A Sin", "M Audier "], "Citations_Link": "https://scholar.google.com/scholar?cites=12518754204266932912&as_sdt=2005&sciodt=0,5&hl=en&num=20"}, {"Paper_link": null, "Title": "[CITATION][C] The Defect Structures in Rare Earth Manganites", "authors": ["S Ueno", "N Kamegashira "], "Citations_Link": "https://scholar.google.com/scholar?q=related:Xw7uk_hcKqcJ:scholar.google.com/&hl=en&num=20&as_sdt=0,5&sciodt=0,5"}], "paper_link": "https://scholar.google.com/citations?view_op=view_citation&hl=en&user=Zs9227oAAAAJ&cstart=1659&pagesize=100&citation_for_view=Zs9227oAAAAJ:tfDI-GPdlUQC", "authors": ["L Sudheendra", "AR Raju", "CNR Rao"], "title": "CMR and related properties of single crystals of cation-deficient LaMnO 3", "publication": "International Journal of Inorganic Materials 2 (6), 657-660, 2000"}